spectrafit/__init__.py
spectrafit/plotting.py
spectrafit/report.py
spectrafit/spectrafit.py
spectrafit/tools.py
spectrafit/api/__init__.py
spectrafit/api/cmd_model.py
spectrafit/api/file_model.py
spectrafit/api/model_utils.py
spectrafit/api/models_model.py
spectrafit/api/moessbauer_model.py
spectrafit/api/notebook_model.py
spectrafit/api/physical_constants.py
spectrafit/api/pptx_model.py
spectrafit/api/report_model.py
spectrafit/api/rixs_model.py
spectrafit/api/tools_model.py
spectrafit/app/__init__.py
spectrafit/app/app.py
spectrafit/models/__init__.py
spectrafit/models/builtin.py
spectrafit/models/moessbauer.py
spectrafit/models/regular.py
spectrafit/plugins/__init__.py
spectrafit/plugins/color_schemas.py
spectrafit/plugins/converter.py
spectrafit/plugins/data_converter.py
spectrafit/plugins/file_converter.py
spectrafit/plugins/notebook.py
spectrafit/plugins/pkl_converter.py
spectrafit/plugins/pkl_visualizer.py
spectrafit/plugins/pptx_converter.py
spectrafit/plugins/rixs_converter.py
spectrafit/plugins/rixs_visualizer.py
spectrafit/plugins/img/SpectraFit.png
spectrafit/utilities/__init__.py
spectrafit/utilities/transformer.py
spectrafit-1.4.0.dist-info/METADATA
spectrafit-1.4.0.dist-info/WHEEL
spectrafit-1.4.0.dist-info/entry_points.txt
spectrafit-1.4.0.dist-info/licenses/LICENSE
spectrafit-1.4.0.dist-info/RECORD
