Metadata-Version: 2.4
Name: SpectraFit
Version: 1.4.0
Summary: Fast fitting of 2D- and 3D-Spectra with established routines
Project-URL: Homepage, https://pypi.org/project/spectrafit/
Project-URL: Repository, https://github.com/Anselmoo/spectrafit
Project-URL: Documentation, https://anselmoo.github.io/spectrafit/
Project-URL: Changelog, https://github.com/Anselmoo/spectrafit/blob/main/CHANGELOG.md
Project-URL: Issues, https://github.com/Anselmoo/spectrafit/issues
Author-email: Anselm Hahn <anselm.hahn@gmail.com>
Maintainer-email: Anselm Hahn <anselm.hahn@gmail.com>
License-Expression: BSD-3-Clause
License-File: LICENSE
Keywords: 2D-Spectra,3D-Spectra,curve-fitting,fitting,peak-fitting,spectrum
Classifier: Development Status :: 5 - Production/Stable
Classifier: Environment :: Console
Classifier: Framework :: Jupyter :: JupyterLab
Classifier: Framework :: Matplotlib
Classifier: Intended Audience :: Science/Research
Classifier: License :: OSI Approved :: BSD License
Classifier: Operating System :: OS Independent
Classifier: Programming Language :: Python :: 3.9
Classifier: Programming Language :: Python :: 3.10
Classifier: Programming Language :: Python :: 3.11
Classifier: Programming Language :: Python :: 3.12
Classifier: Programming Language :: Python :: 3.13
Classifier: Programming Language :: Python :: Implementation :: CPython
Classifier: Topic :: Scientific/Engineering :: Chemistry
Classifier: Topic :: Scientific/Engineering :: Information Analysis
Classifier: Topic :: Scientific/Engineering :: Physics
Requires-Python: <3.14,>=3.9
Requires-Dist: art>=6.5
Requires-Dist: emcee>=3.1.6
Requires-Dist: eval-type-backport>=0.2.2
Requires-Dist: lmfit>=1.3.2
Requires-Dist: numdifftools>=0.9.41
Requires-Dist: numpy>=1.24.4
Requires-Dist: openpyxl>=3.1.5
Requires-Dist: pandas>=2.0.3
Requires-Dist: pydantic>=2.10.6
Requires-Dist: pyyaml>=6.0.2
Requires-Dist: scikit-learn>=1.3.2
Requires-Dist: scipy>=1.10.1
Requires-Dist: seaborn>=0.13.2
Requires-Dist: tabulate>=0.9.0
Requires-Dist: tomli-w>=1.0.0
Requires-Dist: tomli>=2.2.1
Requires-Dist: tqdm>=4.67.1
Provides-Extra: all
Requires-Dist: dash-bootstrap-components>=1.6.0; extra == 'all'
Requires-Dist: dash-bootstrap-templates>=2.1.0; extra == 'all'
Requires-Dist: dtale>=3.17.0; extra == 'all'
Requires-Dist: ipywidgets>=8.1.6; extra == 'all'
Requires-Dist: itables>=2.3.0; extra == 'all'
Requires-Dist: jupyter-dash>=0.4.2; extra == 'all'
Requires-Dist: jupyterlab>=4.3.6; extra == 'all'
Requires-Dist: kaleido>=0.2.1; extra == 'all'
Requires-Dist: networkx>=3.1; extra == 'all'
Requires-Dist: plotly>=6.0.1; extra == 'all'
Requires-Dist: pydot>=3.0.4; extra == 'all'
Requires-Dist: python-pptx>=1.0.2; extra == 'all'
Provides-Extra: graph
Requires-Dist: networkx>=3.1; extra == 'graph'
Requires-Dist: pydot>=3.0.4; extra == 'graph'
Provides-Extra: jupyter
Requires-Dist: dtale>=3.17.0; extra == 'jupyter'
Requires-Dist: itables>=2.3.0; extra == 'jupyter'
Requires-Dist: jupyterlab>=4.3.6; extra == 'jupyter'
Requires-Dist: kaleido==0.2.1; extra == 'jupyter'
Requires-Dist: plotly>=6.0.1; extra == 'jupyter'
Requires-Dist: python-pptx>=1.0.2; extra == 'jupyter'
Provides-Extra: jupyter-dash
Requires-Dist: dash-bootstrap-components>=1.6.0; extra == 'jupyter-dash'
Requires-Dist: dash-bootstrap-templates>=2.1.0; extra == 'jupyter-dash'
Requires-Dist: ipywidgets>=8.1.6; extra == 'jupyter-dash'
Requires-Dist: jupyter-dash>=0.4.2; extra == 'jupyter-dash'
